nutrient_sdk/__init__.py
nutrient_sdk/aiaugmentersettings.py
nutrient_sdk/base_exception.py
nutrient_sdk/cadsettings.py
nutrient_sdk/claudeapisettings.py
nutrient_sdk/color.py
nutrient_sdk/contentextractionsettings.py
nutrient_sdk/conversionsettings.py
nutrient_sdk/customvlmapisettings.py
nutrient_sdk/descriptionlevel.py
nutrient_sdk/digitalsignatureoptions.py
nutrient_sdk/document.py
nutrient_sdk/documentformat.py
nutrient_sdk/documentlayoutjsonexportsettings.py
nutrient_sdk/documentmarkupmode.py
nutrient_sdk/documentsettings.py
nutrient_sdk/documenttype.py
nutrient_sdk/finalizersettings.py
nutrient_sdk/htmlexporter.py
nutrient_sdk/htmllayouttype.py
nutrient_sdk/htmlsettings.py
nutrient_sdk/iexporter.py
nutrient_sdk/imageexporter.py
nutrient_sdk/imageexportformat.py
nutrient_sdk/imagesettingmode.py
nutrient_sdk/imagesettings.py
nutrient_sdk/implicitconversion.py
nutrient_sdk/inferencelayoutsettings.py
nutrient_sdk/internallogic.py
nutrient_sdk/jbig2settings.py
nutrient_sdk/jpegsettings.py
nutrient_sdk/jsonexportcontent.py
nutrient_sdk/jsonexportformat.py
nutrient_sdk/license.py
nutrient_sdk/markdownexporter.py
nutrient_sdk/ocrsettings.py
nutrient_sdk/openaiapiendpointsettings.py
nutrient_sdk/openailanguagesdetectionsettings.py
nutrient_sdk/openaipicturealtsettings.py
nutrient_sdk/opensettings.py
nutrient_sdk/opensettingsmode.py
nutrient_sdk/pagecachemode.py
nutrient_sdk/pdfannotation.py
nutrient_sdk/pdfannotationcollection.py
nutrient_sdk/pdfborderstyle.py
nutrient_sdk/pdfcheckboxfield.py
nutrient_sdk/pdfcircleannotation.py
nutrient_sdk/pdfcomboboxfield.py
nutrient_sdk/pdfcompression.py
nutrient_sdk/pdfconformance.py
nutrient_sdk/pdfeditor.py
nutrient_sdk/pdfexporter.py
nutrient_sdk/pdfformfield.py
nutrient_sdk/pdfformfieldcollection.py
nutrient_sdk/pdfformfieldtype.py
nutrient_sdk/pdffreetextannotation.py
nutrient_sdk/pdfhighlightannotation.py
nutrient_sdk/pdflineannotation.py
nutrient_sdk/pdflineendingstyle.py
nutrient_sdk/pdflinkannotation.py
nutrient_sdk-1.0.1.dist-info/licenses/ACKNOWLEDGEMENTS.md
nutrient_sdk-1.0.1.dist-info/METADATA
nutrient_sdk-1.0.1.dist-info/WHEEL
nutrient_sdk-1.0.1.dist-info/top_level.txt
nutrient_sdk-1.0.1.dist-info/RECORD
