Metadata-Version: 2.4
Name: nutrient-sdk
Version: 1.0.1
Summary: Nutrient SDK Python bindings for document processing
Author-email: Nutrient <support@nutrient.io>
License: Proprietary
Project-URL: Homepage, https://nutrient.io
Project-URL: Documentation, https://nutrient.io/docs
Project-URL: Repository, https://github.com/nutrient/nutrient-sdk-python
Project-URL: Changelog, https://github.com/nutrient/nutrient-sdk-python/blob/main/CHANGELOG.md
Keywords: pdf,document,conversion,nutrient
Classifier: Development Status :: 4 - Beta
Classifier: Intended Audience :: Developers
Classifier: Programming Language :: Python :: 3
Classifier: Programming Language :: Python :: 3.8
Classifier: Programming Language :: Python :: 3.9
Classifier: Programming Language :: Python :: 3.10
Classifier: Programming Language :: Python :: 3.11
Classifier: Programming Language :: Python :: 3.12
Classifier: Operating System :: MacOS
Classifier: Operating System :: POSIX :: Linux
Classifier: Operating System :: Microsoft :: Windows
Requires-Python: >=3.8
License-File: ACKNOWLEDGEMENTS.md
Requires-Dist: nutrient-sdk-native==1.0.1
Provides-Extra: dev
Requires-Dist: pytest>=7.0; extra == "dev"
Requires-Dist: black>=23.0; extra == "dev"
Requires-Dist: mypy>=1.0; extra == "dev"
Dynamic: license-file
